[
{"name": "Whirlpool SP40 802 EU", "price": 36178.0, "url": "/ua/bt-holodilniki/whirlpool-sp40-802-eu/", "title": "Холодильник з морозильною камерою •  вбудований •  А + + •  розміри (ШхВхД): 69x193,5x54,5 см •  холодильна камера: 299 л •  морозильна камера: 101 л •  розморожування морозильної камери: ручне •  білий\n            \n              • 09.2018"},
{"name": "Indesit LI8S1ES", "price": 16008.0, "url": "/ua/bt-holodilniki/indesit-li8s1es/", "title": "Холодильник з морозильною камерою •  окрема •  розміри (ШхВхД): 59,5x188,9x65,5 см •  холодильна камера: 228 л •  морозильна камера: 111 л •  розморожування морозильної камери: LowFrost •  нержавіюча сталь\n            \n              • 07.2021"},
{"name": "Beko BCNA306E3S", "price": 26042.0, "url": "/ua/bt-holodilniki/beko-bcna306e3s/", "title": "Холодильник з морозильною камерою •  вбудований •  А + + •  розміри (ШхВхД): 54x193x54,5 см •  холодильна камера: 215 л •  морозильна камера: 69 л •  розморожування морозильної камери: No Frost •  білий\n            \n              • 05.2019"},
{"name": "Samsung RS66A8100B1", "price": 45340.0, "url": "/ua/bt-holodilniki/samsung-rs66a8100b1/", "title": "Холодильник з морозильною камерою •  окрема •  розміри (ШхВхД): 91,2x178x71,6 см •  холодильна камера: 409 л •  морозильна камера: 243 л •  розморожування морозильної камери: No Frost •  нержавіюча сталь\n            \n              • 05.2021"},
{"name": "LG GW-B509SLKM", "price": 23588.0, "url": "/ua/bt-holodilniki/lg-gw-b509slkm/", "title": "Холодильник з морозильною камерою •  окрема •  А + + •  розміри (ШхВхД): 59,5x203x68,2 см •  холодильна камера: 277 л •  морозильна камера: 107 л •  розморожування морозильної камери: No Frost •  нержавіюча сталь\n            \n              • 03.2019"},
{"name": "Bosch KGN39VI306", "price": 24460.0, "url": "/ua/bt-holodilniki/bosch-kgn39vi306/", "title": "Холодильник з морозильною камерою •  окрема •  А + + •  розміри (ШхВхД): 60x203x66 см •  холодильна камера: 279 л •  морозильна камера: 87 л •  розморожування морозильної камери: No Frost •  нержавіюча сталь\n            \n              • 10.2019"},
{"name": "Indesit LI8S1EW", "price": 15264.0, "url": "/ua/bt-holodilniki/indesit-li8s1ew/", "title": "Холодильник з морозильною камерою •  окрема •  А + •  розміри (ШхВхД): 59,5x187x65,5 см •  холодильна камера: 213 л •  морозильна камера: 90 л •  розморожування морозильної камери: ручне •  білий\n            \n              • 07.2021"},
{"name": "Vestfrost CX 232 W", "price": 9756.0, "url": "/ua/bt-holodilniki/vestfrost-cx-232-w/", "title": "Холодильник з морозильною камерою •  окрема •  A + •  розміри (ШхВхД): 54x144x57 см •  холодильна камера: 171 л •  морозильна камера: 42 л •  розморожування морозильної камери: ручне •  білий\n            \n              • 07.2018"},
{"name": "Gorenje NRS918EMX", "price": 36307.0, "url": "/ua/bt-holodilniki/gorenje-nrs918emx/", "title": "Холодильник з морозильною камерою •  окрема •  A ++ •  розміри (ШхВхД): 91x178,6x64,3 см •  холодильна камера: 334 л •  морозильна камера: 174 л •  розморожування морозильної камери: No Frost •  нержавіюча сталь\n            \n              • 03.2021"},
{"name": "Candy CCE4T618EWU", "price": 17234.0, "url": "/ua/bt-holodilniki/candy-cce4t618ewu/", "title": "Холодильник з морозильною камерою •  окрема •  A ++ •  розміри (ШхВхД): 59,5x185x65,8 см •  холодильна камера: 222 л •  морозильна камера: 119 л •  розморожування морозильної камери: No Frost •  білий\n            \n              • 02.2022"},
{"name": "Bosch KGN39UL316", "price": 22569.0, "url": "/ua/bt-holodilniki/bosch-kgn39ul316/", "title": "Холодильник з морозильною камерою •  окрема •  А + + •  розміри (ШхВхД): 60x203x66 см •  холодильна камера: 279 л •  морозильна камера: 87 л •  розморожування морозильної камери: No Frost •  нержавіюча сталь\n            \n              • 09.2019"},
{"name": "Candy CHTOP 482WN", "price": 6734.0, "url": "/ua/bt-holodilniki/candy-chtop-482wn/", "title": "Холодильник з морозильною камерою •  окрема •  розміри (ШхВхД): 48x85x45 см •  холодильна камера: 93 л •  розморожування морозильної камери: ручне •  білий\n            \n              • 04.2022"},
{"name": "Samsung BRB307154WW", "price": 39620.0, "url": "/ua/bt-holodilniki/samsung-brb307154wwua/", "title": "Холодильник з морозильною камерою •  вбудований •  А + •  розміри (ШхВхД): 54x193,5x55 см •  холодильна камера: 222 л •  морозильна камера: 72 л •  розморожування морозильної камери: No Frost •  білий\n            \n              • 06.2021"},
{"name": "Indesit LI9S1EW", "price": 15859.0, "url": "/ua/bt-holodilniki/indesit-li9s1ew/", "title": "Холодильник з морозильною камерою •  окрема •  А + •  розміри (ШхВхД): 59,5x201,3x65,5 см •  холодильна камера: 261 л •  морозильна камера: 111 л •  розморожування морозильної камери: ручне •  білий\n            \n              • 08.2021"},
{"name": "LG GA-B509SLSM", "price": 22619.0, "url": "/ua/bt-holodilniki/lg-ga-b509slsm/", "title": "Холодильник з морозильною камерою •  окрема •  А + + •  розміри (ШхВхД): 59,5x203x68,2 см •  холодильна камера: 207 л •  морозильна камера: 107 л •  розморожування морозильної камери: No Frost •  нержавіюча сталь\n            \n              • 03.2021"},
{"name": "Whirlpool ART 65021", "price": 15628.0, "url": "/ua/bt-holodilniki/whirlpool-art-65021/", "title": "Холодильник з морозильною камерою •  вбудований •  розміри (ШхВхД): 54x177x54,5 см •  холодильна камера: 194 л •  морозильна камера: 79 л •  розморожування морозильної камери: LessFrost •  білий\n            \n              • 03.2021"},
{"name": "Samsung BRB266050WW", "price": 25809.0, "url": "/ua/bt-holodilniki/samsung-brb266050wwua/", "title": "Холодильник з морозильною камерою •  вбудований •  А + •  розміри (ШхВхД): 54x177,5x55 см •  холодильна камера: 192 л •  морозильна камера: 72 л •  розморожування морозильної камери: No Frost •  білий\n            \n              • 05.2021"},
{"name": "Bosch KGN36NL306", "price": 18124.0, "url": "/ua/bt-holodilniki/bosch-kgn36nl306/", "title": "Холодильник з морозильною камерою •  окрема •  A ++ •  розміри (ШхВхД): 60x186x66 см •  холодильна камера: 215 л •  морозильна камера: 87 л •  розморожування морозильної камери: No Frost •  нержавіюча сталь\n            \n              • 07.2017"},
{"name": "Samsung RB34T600FSA", "price": 21430.0, "url": "/ua/bt-holodilniki/samsung-rb34t600fsa/", "title": "Холодильник з морозильною камерою •  окрема •  А + •  розміри (ШхВхД): 59,5x185,3x65,8 см •  холодильна камера: 228 л •  морозильна камера: 112 л •  розморожування морозильної камери: No Frost •  сріблястий\n            \n              • 11.2020"},
{"name": "Gorenje NRM8181MX", "price": 31850.0, "url": "/ua/bt-holodilniki/gorenje-nrm8181mx/", "title": "Холодильник з морозильною камерою •  окрема •  А + •  розміри (ШхВхД): 79,4x181,6x64,3 см •  холодильна камера: 265 л •  морозильна камера: 129 л •  розморожування морозильної камери: No Frost •  нержавіюча сталь\n            \n              • 01.2020"},
{"name": "Siemens KG39NAI306", "price": 28179.0, "url": "/ua/bt-holodilniki/siemens-kg39nai306/", "title": "Холодильник з морозильною камерою •  окрема •  А + + •  розміри (ШхВхД): 60x203x66 см •  холодильна камера: 279 л •  морозильна камера: 87 л •  розморожування морозильної камери: No Frost •  нержавіюча сталь\n            \n              • 03.2021"},
{"name": "Sharp SJ-TB01ITXLE", "price": 12214.0, "url": "/ua/bt-holodilniki/sharp-sj-tb01itxle/", "title": "Холодильник з морозильною камерою •  окрема •  розміри (ШхВхД): 54x145x57 см •  холодильна камера: 171 л •  морозильна камера: 42 л •  розморожування морозильної камери: NanoFrost •  нержавіюча сталь\n            \n              • 05.2022"},
{"name": "Gorenje NRS8181KX", "price": 29983.0, "url": "/ua/bt-holodilniki/gorenje-nrs8181kx/", "title": "Холодильник з морозильною камерою •  окрема •  A + •  розміри (ШхВхД): 83,2x 177,7 x63,2  см •  холодильна камера: 264 л •  морозильна камера: 164 л •  розморожування морозильної камери: No Frost •  сріблястий\n            \n              • 01.2021"},
{"name": "Samsung RS66A8100S9", "price": 45363.0, "url": "/ua/bt-holodilniki/samsung-rs66a8100s9ua/", "title": "Холодильник з морозильною камерою •  окрема •  А + •  розміри (ШхВхД): 91,2x178x71,6 см •  холодильна камера: 403 л •  морозильна камера: 238 л •  розморожування морозильної камери: No Frost •  нержавіюча сталь\n            \n              • 03.2021"},
{"name": "Bosch KGV36UW206", "price": 14725.0, "url": "/ua/bt-holodilniki/bosch-kgv36uw206/", "title": "Холодильник з морозильною камерою •  окрема •  A + •  розміри (ШхВхД): 60x186x65 см •  холодильна камера: 214 л •  морозильна камера: 94 л •  розморожування морозильної камери: LowFrost •  білий\n            \n              • 02.2018"},
{"name": "Bosch KGN36VL326", "price": 19652.0, "url": "/ua/bt-holodilniki/bosch-kgn36vl326/", "title": "Холодильник з морозильною камерою •  окрема •  А + + •  розміри (ШхВхД): 60x186x66 см •  холодильна камера: 237 л •  морозильна камера: 87 л •  розморожування морозильної камери: No Frost •  нержавіюча сталь\n            \n              • 09.2019"},
{"name": "Samsung RB38T676FSA", "price": 24395.0, "url": "/ua/bt-holodilniki/samsung-rb38t676fsa/", "title": "Холодильник з морозильною камерою •  окрема •  А + •  розміри (ШхВхД): 59,5x203x65,8 см •  холодильна камера: 273 л •  морозильна камера: 112 л •  розморожування морозильної камери: No Frost •  нержавіюча сталь\n            \n              • 11.2020"},
{"name": "Indesit LI6 S1E W", "price": 13201.0, "url": "/ua/bt-holodilniki/indesit-li6-s1e-w/", "title": "Холодильник з морозильною камерою •  окрема •  розміри (ШхВхД): 59,5x158,8x65,5 см •  холодильна камера: 197 л •  морозильна камера: 75 л •  розморожування морозильної камери: LowFrost •  білий\n            \n              • 08.2021"},
{"name": "Liebherr CU 3331", "price": 17137.0, "url": "/ua/bt-holodilniki/liebherr-cu-3331/", "title": "Холодильник з морозильною камерою •  окрема •  А + + •  розміри (ШхВхД): 55x181,2x63 см •  холодильна камера: 212 л •  морозильна камера: 84 л •  розморожування морозильної камери: ручне •  білий\n            \n              • 02.2019"},
{"name": "Bosch KGN39XI326", "price": 25172.0, "url": "/ua/bt-holodilniki/bosch-kgn39xi326/", "title": "Холодильник з морозильною камерою •  окрема •  А + + •  розміри (ШхВхД): 60x200x66 см •  холодильна камера: 279 л •  морозильна камера: 87 л •  розморожування морозильної камери: No Frost •  нержавіюча сталь\n            \n              • 11.2019"},
{"name": "Bosch KGN33NL206", "price": 17187.0, "url": "/ua/bt-holodilniki/bosch-kgn33nl206/", "title": "Холодильник з морозильною камерою •  окрема •  A + •  розміри (ШхВхД): 60x176x66 см •  холодильна камера: 192 л •  морозильна камера: 87 л •  розморожування морозильної камери: No Frost •  нержавіюча сталь\n            \n              • 07.2017"},
{"name": "Bosch KGN39XW326", "price": 24020.0, "url": "/ua/bt-holodilniki/bosch-kgn39xw326/", "title": "Холодильник з морозильною камерою •  окрема •  А + + •  розміри (ШхВхД): 60x203x66 см •  холодильна камера: 279 л •  морозильна камера: 87 л •  розморожування морозильної камери: No Frost •  білий\n            \n              • 12.2020"},
{"name": "Gorenje RK4181PS4", "price": 14549.0, "url": "/ua/bt-holodilniki/gorenje-rk4181ps4/", "title": "Холодильник з морозильною камерою •  окрема •  А + •  розміри (ШхВхД): 55x180x55,7 см •  холодильна камера: 198 л •  морозильна камера: 66 л •  розморожування морозильної камери: ручне •  нержавіюча сталь\n            \n              • 01.2021"},
{"name": "Whirlpool ART 6711/A++ SF", "price": 20026.0, "url": "/ua/bt-holodilniki/whirlpool-art-6711aplusplus-sf/", "title": "Холодильник з морозильною камерою •  вбудований •  A ++ •  розміри (ШхВхД): 54x177x54,5 см •  холодильна камера: 195 л •  морозильна камера: 80 л •  розморожування морозильної камери: No Frost •  білий\n            \n              • 07.2014"},
{"name": "Samsung RB38T600FSA", "price": 22340.0, "url": "/ua/bt-holodilniki/samsung-rb38t600fsa/", "title": "Холодильник з морозильною камерою •  окрема •  A + •  розміри (ШхВхД): 59,5x203x65,8 см •  холодильна камера: 273 л •  морозильна камера: 112 л •  розморожування морозильної камери: No Frost •  металевий графіт\n            \n              • 11.2021"},
{"name": "Samsung BRB307054WW", "price": 33432.0, "url": "/ua/bt-holodilniki/samsung-brb307054wwua/", "title": "Холодильник з морозильною камерою •  вбудований •  А + •  розміри (ШхВхД): 54x193,5x55 см •  холодильна камера: 222 л •  морозильна камера: 72 л •  розморожування морозильної камери: No Frost •  білий\n            \n              • 06.2021"},
{"name": "Indesit LI7 S1E W", "price": 14235.0, "url": "/ua/bt-holodilniki/indesit-li7-s1e-w/", "title": "Холодильник з морозильною камерою •  окрема •  А + •  розміри (ШхВхД): 59,5x176x65,5 см •  холодильна камера: 197 л •  морозильна камера: 111 л •  розморожування морозильної камери: ручне •  білий\n            \n              • 05.2022"},
{"name": "Bosch KGN33NW206", "price": 16898.0, "url": "/ua/bt-holodilniki/bosch-kgn33nw206/", "title": "Холодильник з морозильною камерою •  окрема •  A + •  розміри (ШхВхД): 60x176x66 см •  холодильна камера: 192 л •  морозильна камера: 87 л •  розморожування морозильної камери: No Frost •  білий\n            \n              • 07.2017"},
{"name": "Grunhelm GRW-138DD", "price": 9407.0, "url": "/ua/bt-holodilniki/grunhelm-grw-138dd/", "title": "Холодильник з морозильною камерою •  окрема •  А + •  розміри (ШхВхД): 53x137x48 см •  холодильна камера: 93 л •  морозильна камера: 45 л •  розморожування морозильної камери: ручне •  білий\n            \n              • 03.2019"},
{"name": "Whirlpool SP40 801 EU", "price": 31074.0, "url": "/ua/bt-holodilniki/whirlpool-sp40-801-eu/", "title": "Холодильник з морозильною камерою •  вбудований •  A + •  розміри (ШхВхД): 69x193,5x54,5 см •  холодильна камера: 299 л •  морозильна камера: 101 л •  розморожування морозильної камери: ручне •  білий\n            \n              • 12.2017"},
{"name": "Bosch KGV39VW316", "price": 17549.0, "url": "/ua/bt-holodilniki/bosch-kgv39vw316/", "title": "Холодильник з морозильною камерою •  окрема •  А + + •  розміри (ШхВхД): 60x201x65 см •  холодильна камера: 249 л •  морозильна камера: 94 л •  розморожування морозильної камери: LowFrost •  білий\n            \n              • 09.2020"},
{"name": "LG GW-B509SMUM", "price": 25959.0, "url": "/ua/bt-holodilniki/lg-gw-b509smum/", "title": "Холодильник з морозильною камерою •  окрема •  А + + •  розміри (ШхВхД): 59,5x203x68,2 см •  холодильна камера: 277 л •  морозильна камера: 107 л •  розморожування морозильної камери: No Frost •  нержавіюча сталь\n            \n              • 03.2021"},
{"name": "Bosch KGN49XL306", "price": 32822.0, "url": "/ua/bt-holodilniki/bosch-kgn49xl306/", "title": "Холодильник з морозильною камерою •  окрема •  A ++ •  розміри (ШхВхД): 70x203x66 см •  холодильна камера: 330 л •  морозильна камера: 105 л •  розморожування морозильної камери: No Frost •  нержавіюча сталь\n            \n              • 10.2018"},
{"name": "Whirlpool W7X 82O OX", "price": 19709.0, "url": "/ua/bt-holodilniki/whirlpool-w7x-82o-ox/", "title": "Холодильник з морозильною камерою •  окрема •  розміри (ШхВхД): 59,6x191,2x67,8 см •  холодильна камера: 231 л •  морозильна камера: 104 л •  розморожування морозильної камери: No Frost •  нержавіюча сталь\n            \n              • 08.2022"},
{"name": "Bosch KGN39VL316", "price": 23696.0, "url": "/ua/bt-holodilniki/bosch-kgn39vl316/", "title": "Холодильник з морозильною камерою •  окрема •  А + + •  розміри (ШхВхД): 60x203x66 см •  холодильна камера: 279 л •  морозильна камера: 87 л •  розморожування морозильної камери: No Frost •  нержавіюча сталь\n            \n              • 12.2020"},
{"name": "Whirlpool W5 811E OX", "price": 16566.0, "url": "/ua/bt-holodilniki/whirlpool-w5811eox/", "title": "Холодильник з морозильною камерою •  окрема •  А + •  розміри (ШхВхД): 59,5x188,8x65,6 см •  холодильна камера: 228 л •  морозильна камера: 111 л •  розморожування морозильної камери: LessFrost •  нержавіюча сталь\n            \n              • 05.2019"},
{"name": "Gorenje NRK6202AXL4", "price": 22260.0, "url": "/ua/bt-holodilniki/gorenje-nrk6202axl4/", "title": "Холодильник з морозильною камерою •  окрема •  А + + •  розміри (ШхВхД): 60x200x59,2 см •  холодильна камера: 235 л •  морозильна камера: 96 л •  розморожування морозильної камери: No Frost •  нержавіюча сталь\n            \n              • 07.2020"},
{"name": "LG GA-B379SLUL", "price": 25166.0, "url": "/ua/bt-holodilniki/lg-ga-b379slul/", "title": "Холодильник з морозильною камерою •  окрема •  A + •  розміри (ШхВхД): 59,5x173,7x65,5 см •  холодильна камера: 182 л •  морозильна камера: 79 л •  розморожування морозильної камери: No Frost •  нержавіюча сталь\n            \n              • 11.2018"},
{"name": "Siemens KG39NXX316", "price": 26624.0, "url": "/ua/bt-holodilniki/bosch-kg39nxx316/", "title": "Холодильник з морозильною камерою •  окрема •  А + + •  розміри (ШхВхД): 60x203x66 см •  холодильна камера: 279 л •  морозильна камера: 87 л •  розморожування морозильної камери: No Frost •  чорний\n            \n              • 10.2019"},
{"name": "Beko RCNE560E35ZXB", "price": 28424.0, "url": "/ua/bt-holodilniki/beko-rcne560e35zxb/", "title": "Холодильник з морозильною камерою •  окрема •  А + + •  розміри (ШхВхД): 70x192x74,5 см •  холодильна камера: 356 л •  морозильна камера: 145 л •  розморожування морозильної камери: No Frost •  нержавіюча сталь\n            \n              • 06.2020"},
{"name": "Samsung RB36T677FEL", "price": 22545.0, "url": "/ua/bt-holodilniki/samsung-rb36t677fel/", "title": "Холодильник з морозильною камерою •  окрема •  А + •  розміри (ШхВхД): 59,5x193,5x65,8 см •  холодильна камера: 248 л •  морозильна камера: 112 л •  розморожування морозильної камери: No Frost •  бежевий\n            \n              • 02.2022"},
{"name": "Samsung RB38T600ESA", "price": 22325.0, "url": "/ua/bt-holodilniki/samsung-rb38t600esa/", "title": "Холодильник з морозильною камерою •  окрема •  А + + •  розміри (ШхВхД): 59,5x203x65,8 см •  холодильна камера: 276 л •  морозильна камера: 114 л •  розморожування морозильної камери: No Frost •  нержавіюча сталь\n            \n              • 03.2021"},
{"name": "Eleyus RLW 2146 M", "price": 10999.0, "url": "/ua/bt-holodilniki/eleyus-rlw-2146-m/", "title": "Холодильник з морозильною камерою •  окрема •  А + •  холодильна камера: 112 л •  морозильна камера: 61 л •  розморожування морозильної камери: FrostLess •  білий\n            \n              • 12.2022"},
{"name": "Samsung RZ32M7110SA", "price": 27352.0, "url": "/ua/bt-holodilniki/samsung-rz32m7110sa/", "title": "Морозильна камера •  окрема •  розміри (ШхВхД): 59,5x185,3x69,4 см •  морозильна камера: 315 л •  розморожування морозильної камери: No Frost •  нержавіюча сталь\n            \n              • 10.2020"},
{"name": "LG GW-B459SLCM", "price": 22431.0, "url": "/ua/bt-holodilniki/lg-gw-b459slcm/", "title": "Холодильник з морозильною камерою •  окрема •  A ++ •  розміри (ШхВхД): 59,5x186x68,2 см •  холодильна камера: 234 л •  морозильна камера: 107 л •  розморожування морозильної камери: No Frost •  графіт\n            \n              • 03.2019"},
{"name": "Whirlpool W9 931D KS", "price": 26026.0, "url": "/ua/bt-holodilniki/whirlpool-w9-931d-ks/", "title": "Холодильник з морозильною камерою •  окрема •  А + + + •  розміри (ШхВхД): 59,5x201,1x66,3 см •  холодильна камера: 251 л •  морозильна камера: 97 л •  розморожування морозильної камери: No Frost •  чорний\n            \n              • 06.2019"},
{"name": "Indesit LI9S1ES", "price": 16743.0, "url": "/ua/bt-holodilniki/indesit-li9s1es/", "title": "Холодильник з морозильною камерою •  окрема •  А + •  розміри (ШхВхД): 59,5x201,3x65,5 см •  холодильна камера: 261 л •  морозильна камера: 111 л •  розморожування морозильної камери: ручне •  нержавіюча сталь\n            \n              • 08.2021"},
{"name": "Hotpoint-Ariston HAC20 T321", "price": 23387.0, "url": "/ua/bt-holodilniki/hotpoint-ariston-hac20-t321/", "title": "Холодильник з морозильною камерою •  вбудований •  розміри (ШхВхД): 54x193,5x54,5 см •  холодильна камера: 212 л •  морозильна камера: 68 л •  розморожування морозильної камери: No Frost •  білий\n            \n              • 09.2021"},
{"name": "Bosch KGN49MIEA", "price": 32546.0, "url": "/ua/bt-holodilniki/bosch-kgn49miea/", "title": "Холодильник з морозильною камерою •  окрема •  A ++ •  розміри (ШхВхД): 70x203x67 см •  холодильна камера: 330 л •  морозильна камера: 108 л •  розморожування морозильної камери: No Frost •  нержавіюча сталь\n            \n              • 02.2021"},
{"name": "Ardesto FRM-200E", "price": 9092.0, "url": "/ua/bt-holodilniki/ardesto-frm-200e/", "title": "Морозильна скриня •  окрема •  А + •  розміри (ШхВхД): 94,5x85x52,3 см •  морозильна камера: 198 л •  розморожування морозильної камери: ручне •  білий\n            \n              • 07.2019"},
{"name": "Gorenje RK6201ES4", "price": 17555.0, "url": "/ua/bt-holodilniki/gorenje-rk6201es4/", "title": "Холодильник з морозильною камерою •  окрема •  А + •  розміри (ШхВхД): 60x200x59,2 см •  холодильна камера: 239 л •  морозильна камера: 110 л •  розморожування морозильної камери: FrostLess •  нержавіюча сталь\n            \n              • 11.2020"},
{"name": "Samsung RS62R50314G/UA", "price": 55295.0, "url": "/ua/bt-holodilniki/samsung-rs62r50314gua/", "title": "Холодильник з морозильною камерою •  окрема •  А + •  розміри (ШхВхД): 91,2x178x71,6 см •  холодильна камера: 418 л •  морозильна камера: 229 л •  розморожування морозильної камери: NoFrost •  золотий\n            \n              • 09.2019"},
{"name": "Liebherr CU 2831", "price": 16701.0, "url": "/ua/bt-holodilniki/liebherr-cu-2831/", "title": "Холодильник з морозильною камерою •  окрема •  А + + •  розміри (ШхВхД): 55x161,2x63 см •  холодильна камера: 212 л •  морозильна камера: 53 л •  розморожування морозильної камери: ручне •  білий\n            \n              • 02.2019"},
{"name": "Samsung RB38T776FB1", "price": 26634.0, "url": "/ua/bt-holodilniki/samsung-rb38t776fb1/", "title": "Холодильник з морозильною камерою •  окрема •  А + •  розміри (ШхВхД): 59,5x203x65,8 см •  холодильна камера: 273 л •  морозильна камера: 112 л •  розморожування морозильної камери: No Frost •  нержавіюча сталь\n            \n              • 01.2022"},
{"name": "Whirlpool W7X 81O OX", "price": 18695.0, "url": "/ua/bt-holodilniki/whirlpool-w7x-81o-ox/", "title": "Холодильник з морозильною камерою •  окрема •  розміри (ШхВхД): 59,6x191,2x67,8 см •  холодильна камера: 231 л •  морозильна камера: 104 л •  розморожування морозильної камери: No Frost •  нержавіюча сталь\n            \n              • 08.2022"},
{"name": "Bosch KGN39VW316", "price": 22917.0, "url": "/ua/bt-holodilniki/bosch-kgn39vw316/", "title": "Холодильник з морозильною камерою •  окрема •  А + + •  розміри (ШхВхД): 60x203x66 см •  холодильна камера: 279 л •  морозильна камера: 87 л •  розморожування морозильної камери: No Frost •  білий\n            \n              • 12.2020"},
{"name": "Gorenje NRS918EMB", "price": 36342.0, "url": "/ua/bt-holodilniki/gorenje-nrs918emb/", "title": "Холодильник з морозильною камерою •  окрема •  А + + •  розміри (ШхВхД): 91x178,6x64,3 см •  холодильна камера: 334 л •  морозильна камера: 174 л •  розморожування морозильної камери: No Frost •  чорний\n            \n              • 03.2021"},
{"name": "Liebherr CNf 5703 Pure", "price": 25986.0, "url": "/ua/bt-holodilniki/liebherr-cnf-5703-pure/", "title": "Холодильник з морозильною камерою •  окрема •  A •  розміри (ШхВхД): 60,9x201,5x67,5 см •  холодильна камера: 266 л •  морозильна камера: 94 л •  розморожування морозильної камери: No Frost •  білий\n            \n              • 08.2022"},
{"name": "Gorenje NRK62DAXL4", "price": 23921.0, "url": "/ua/bt-holodilniki/gorenje-nrk62daxl4/", "title": "Холодильник з морозильною камерою •  окрема •  А + + •  розміри (ШхВхД): 60x203x66,3 см •  холодильна камера: 255 л •  морозильна камера: 106 л •  розморожування морозильної камери: No Frost •  нержавіюча сталь\n            \n              • 10.2022"},
{"name": "Indesit INFC8 TI21W", "price": 17725.0, "url": "/ua/bt-holodilniki/indesit-infc8-ti21w/", "title": "Холодильник з морозильною камерою •  окрема •  А + •  розміри (ШхВхД): 59,6x191,2x67,8 см •  холодильна камера: 231 л •  морозильна камера: 104 л •  розморожування морозильної камери: No Frost •  білий\n            \n              • 10.2021"},
{"name": "Indesit LI7 SN1E W", "price": 16176.0, "url": "/ua/bt-holodilniki/indesit-li7-sn1e-w/", "title": "Холодильник з морозильною камерою •  окрема •  А + •  розміри (ШхВхД): 59,5x176,3x65,5 см •  холодильна камера: 197 л •  морозильна камера: 98 л •  розморожування морозильної камери: No Frost •  білий\n            \n              • 06.2022"}
]